odoo/addons/shopfloor_workstation_mobile/README.rst
odoo/addons/shopfloor_workstation_mobile/__init__.py
odoo/addons/shopfloor_workstation_mobile/__manifest__.py
odoo/addons/shopfloor_workstation_mobile/i18n/es_AR.po
odoo/addons/shopfloor_workstation_mobile/i18n/pt_BR.po
odoo/addons/shopfloor_workstation_mobile/i18n/shopfloor_workstation_mobile.pot
odoo/addons/shopfloor_workstation_mobile/static/description/icon.png
odoo/addons/shopfloor_workstation_mobile/static/description/index.html
odoo/addons/shopfloor_workstation_mobile/static/wms/src/settings/workstation.js
odoo/addons/shopfloor_workstation_mobile/templates/assets.xml
odoo14_addon_shopfloor_workstation_mobile-14.0.1.0.1.dist-info/METADATA
odoo14_addon_shopfloor_workstation_mobile-14.0.1.0.1.dist-info/WHEEL
odoo14_addon_shopfloor_workstation_mobile-14.0.1.0.1.dist-info/top_level.txt
odoo14_addon_shopfloor_workstation_mobile-14.0.1.0.1.dist-info/RECORD
